lnhistoryclient/Lnhistoryrequster.py
lnhistoryclient/__init__.py
lnhistoryclient/common.py
lnhistoryclient/constants.py
lnhistoryclient/model/Address.py
lnhistoryclient/model/AddressType.py
lnhistoryclient/model/ChannelAnnouncement.py
lnhistoryclient/model/ChannelUpdate.py
lnhistoryclient/model/NodeAnnouncement.py
lnhistoryclient/model/__init__.py
lnhistoryclient/model/types.py
lnhistoryclient/model/core_lightning_internal/ChannelAmount.py
lnhistoryclient/model/core_lightning_internal/ChannelDying.py
lnhistoryclient/model/core_lightning_internal/DeleteChannel.py
lnhistoryclient/model/core_lightning_internal/GossipStoreEnded.py
lnhistoryclient/model/core_lightning_internal/PrivateChannelAnnouncement.py
lnhistoryclient/model/core_lightning_internal/PrivateChannelUpdate.py
lnhistoryclient/model/core_lightning_internal/__init__.py
lnhistoryclient/model/core_lightning_internal/types.py
lnhistoryclient/model/platform_internal/PlatformEvent.py
lnhistoryclient/model/platform_internal/PlatformEventMetadata.py
lnhistoryclient/parser/__init__.py
lnhistoryclient/parser/common.py
lnhistoryclient/parser/gossip_file.py
lnhistoryclient/parser/parser.py
lnhistoryclient/parser/parser_factory.py
lnhistoryclient/parser/parser_map.py
lnhistoryclient/parser/core_lightning_internal/__init__.py
lnhistoryclient/parser/core_lightning_internal/parser.py
lnhistoryclient-3.6.1.dist-info/licenses/LICENSE
lnhistoryclient-3.6.1.dist-info/METADATA
lnhistoryclient-3.6.1.dist-info/WHEEL
lnhistoryclient-3.6.1.dist-info/top_level.txt
lnhistoryclient-3.6.1.dist-info/RECORD
